{
  "AzureWebJobsDashboard": "UseDevelopmentStorage=true",
  "AzureWebJobsStorage": "UseDevelopmentStorage=true",
  "APPINSIGHTS_INSTRUMENTATIONKEY": "<instrumentation key>",
  "EventHubConnectionString": "<event hub connection string>",
  "EventHubName": "test-hub",
  "PartitionStatusTableName": "PartitionStatus",
  "StorageConnectionString": "UseDevelopmentStorage=true",
  "StorageContainerName": "event-metadata",
  "Redis": "http://localhost:6379",
  "Settings__Delay": 0,
  "Settings__SkipAll": true,
  "Settings__TestRun": 1,
  "Settings__DbConnection": "Data Source=(LocalDb)\\MSSQLLocalDB;Initial Catalog=ehconsumer-db-server;Integrated Security=SSPI;",
  "Logging": {
    "LogLevel": {
      "Default": "Trace"
    }
  }
}
